README.txt
setup.py
boois_vali_rule_info/__init__.py
boois_vali_rule_info/vali_rule_info.py
boois_vali_rule_info.egg-info/PKG-INFO
boois_vali_rule_info.egg-info/SOURCES.txt
boois_vali_rule_info.egg-info/dependency_links.txt
boois_vali_rule_info.egg-info/requires.txt
boois_vali_rule_info.egg-info/top_level.txt
boois_vali_rule_info.egg-info/zip-safe