Metadata-Version: 1.1
Name: boois-vali-rule-info
Version: 1.1.2
Summary: boois_vali_rule_info
Home-page: http://www.boois.cn/
Author: boois
Author-email: admin@boois.cn
License: MIT
Keywords: boois_vali_rule_info
Platform: UNKNOWN
Classifier: License :: OSI Approved :: MIT License
Classifier: Programming Language :: Python
Classifier: Intended Audience :: Developers
Classifier: Operating System :: OS Independent
